src/LedDecoder.v
`define CHAR_HYP 4'd10
`define CHAR_F 4'd11
`define CHAR_SP 4'd12

module LedDecoder (
    input  wire [3:0] char,
    output reg  [6:0] led
);

  //        a
  //       ------
  //    f |      | b
  //      |  g   |
  //       ------
  //      |      |
  //    e |      | c
  //       ------
  //         d

  always @(char) begin
    case (char)
      //                  abcdefg
      0:         led = 7'b0000001;
      1:         led = 7'b1001111;
      2:         led = 7'b0010010;
      3:         led = 7'b0000110;
      4:         led = 7'b1001100;
      5:         led = 7'b0100100;
      6:         led = 7'b1100000;
      7:         led = 7'b0001111;
      8:         led = 7'b0000000;
      9:         led = 7'b0001100;
      `CHAR_HYP: led = 7'b1111110;
      `CHAR_F:   led = 7'b0111000;
      `CHAR_SP:  led = 7'b1111111;
      default:   led = 7'b1111111;
    endcase
  end

endmodule

src/LedDriver4.v
`include "LedDecoder.v"

//                                                                                           counter = 15
//                    ┌──────────────────────────────────────────────────────────────────────────────────┐
//                    │                                                                                  │
//                    ▼                                                                                  │
//                ┌───────┐  counter = 15  ┌───────┐  counter = 15   ┌───────┐  counter = 15  ┌───────┐  │
//                │ AN3-3 │ ┌─────────────▶│ AN2-3 │ ┌──────────────▶│ AN1-3 │ ┌─────────────▶│ AN0-3 │  │
//                └───────┘ │              └───────┘ │               └───────┘ │              └───────┘  │
//             clk = 1│     │          clk = 1 │     │            clk = 1│     │          clk = 1 │      │
//                    ▼     │                  ▼     │                   ▼     │                  ▼      │
//                ┌───────┐ │              ┌───────┐ │               ┌───────┐ │              ┌───────┐  │
//                │ AN3-2 │ │              │ AN2-2 │ │               │ AN1-2 │ │              │ AN0-2 │  │
//                └───────┘ │              └───────┘ │               └───────┘ │              └───────┘  │
//       clk = 1      │     │     clk = 1      │     │      clk = 1      │     │     clk = 1      │      │
// (char = msg[15:12])▼     │(char = msg[11:8])▼     │ (char = msg[7:4]) ▼     │(char = msg[3:0]) ▼      │
//                ┌───────┐ │              ┌───────┐ │               ┌───────┐ │              ┌───────┐  │
//                │ AN3-1 │ │              │ AN2-1 │ │               │ AN1-1 │ │              │ AN0-1 │  │
//                └───────┘ │              └───────┘ │               └───────┘ │              └───────┘  │
//            clk = 1 │     │          clk = 1 │     │           clk = 1 │     │          clk = 1 │      │
//           an = 0111▼     │         an = 1011▼     │          an = 1101▼     │         an = 1110▼      │
//                ┌───────┐ │              ┌───────┐ │               ┌───────┐ │              ┌───────┐  │
//             ┌──│  AN3  │─┘           ┌──│  AN2  │─┘            ┌──│  AN1  │─┘           ┌──│  AN0  │──┘
//             │  └───────┘             │  └───────┘              │  └───────┘             │  └───────┘
//             │      ▲                 │      ▲                  │      ▲                 │      ▲
//             │      │                 │      │                  │      │                 │      │
//             └──────┘                 └──────┘                  └──────┘                 └──────┘
//            clk = 1                  clk = 1                   clk = 1                  clk = 1
//          counter+=1               counter+=1                counter+=1               counter+=1
module LedDriver4 (
    input clk,
    reset,
    input wire [15:0] msg,
    output reg [3:0] an,
    output wire [6:0] led_out
);

  reg [3:0] cur_state, next_state, char, counter;

  LedDecoder decoder (
      .led (led_out),
      .char(char)
  );

  parameter AN3 = 4'b1110, AN2 = 4'b1010, AN1 = 4'b0110, AN0 = 4'b0010;

  always @(posedge clk or posedge reset) begin : STATE_MEMORY
    if (reset) begin
      cur_state <= 4'b0001;
      counter   <= 0;
    end else begin
      cur_state <= next_state;
      case (cur_state)
        AN3, AN2, AN1, AN0: counter <= counter + 1;
        default: counter <= 0;
      endcase
    end
  end

  always @(cur_state or counter) begin : NEXT_STATE_LOGIC
    case (cur_state)
      AN3, AN2, AN1, AN0: begin
        if (counter == 15) next_state = cur_state - 1;
      end
      default: next_state = cur_state - 1;
    endcase
  end

  always @(cur_state) begin : OUTPUT_LOGIC
    case (cur_state)
      AN3:     an = 4'b0111;
      AN2:     an = 4'b1011;
      AN1:     an = 4'b1101;
      AN0:     an = 4'b1110;
      4'b0000: char = msg[15:12];
      AN2 + 2: char = msg[11:8];
      AN1 + 2: char = msg[7:4];
      AN0 + 2: char = msg[3:0];
      default: an = 4'b1111;
    endcase
  end

endmodule

src/LedDriver4_tb.v
`timescale 1ns / 1ps
`include "LedDriver4.v"

module LedDriver4_tb;

  reg clk_tb, reset_tb;
  reg [15:0] msg_tb;

  LedDriver4 driver (
      .clk  (clk_tb),
      .reset(reset_tb),
      .msg  (msg_tb)
  );

  always #10 clk_tb = ~clk_tb;

  initial begin
    $dumpfile("waveforms/LedDriver4.vcd");
    $dumpvars;

    clk_tb   = 0;
    reset_tb = 0;
    msg_tb   = {4'b1010, 4'b1011, 4'b0011, 4'b0100};

    #1 reset_tb = 1;
    #1 reset_tb = 0;

    repeat (80) @(posedge clk_tb);
    $finish;
  end

endmodule

waveforms/LedDriver4.vcd
$date
	Sun Dec 25 22:37:08 2022
$end
$version
	Icarus Verilog
$end
$timescale
	1ps
$end
$scope module LedDriver4_tb $end
$var reg 1 ! clk_tb $end
$var reg 16 " msg_tb [15:0] $end
$var reg 1 # reset_tb $end
$scope module driver $end
$var wire 1 ! clk $end
$var wire 16 $ msg [15:0] $end
$var wire 1 # reset $end
$var wire 7 % led_out [6:0] $end
$var reg 4 & an [3:0] $end
$var reg 4 ' char [3:0] $end
$var reg 4 ( counter [3:0] $end
$var reg 4 ) cur_state [3:0] $end
$var reg 4 * next_state [3:0] $end
$scope module decoder $end
$var wire 4 + char [3:0] $end
$var reg 7 , led [6:0] $end
$upscope $end
$scope begin NEXT_STATE_LOGIC $end
$upscope $end
$scope begin OUTPUT_LOGIC $end
$upscope $end
$scope begin STATE_MEMORY $end
$upscope $end
$upscope $end
$upscope $end
$enddefinitions $end
#0
$dumpvars
bx ,
bx +
bx *
bx )
bx (
bx '
bx &
bx %
b1010101100110100 $
0#
b1010101100110100 "
0!
$end
#1000
b1111 &
b0 *
b0 (
b1 )
1#
#2000
0#
#10000
b1111110 %
b1111110 ,
b1010 '
b1010 +
b1111 *
b0 )
1!
#20000
0!
#30000
b1110 *
b1111 )
1!
#40000
0!
#50000
b111 &
b1110 )
1!
#60000
0!
#70000
b1 (
1!
#80000
0!
#90000
b10 (
1!
#100000
0!
#110000
b11 (
1!
#120000
0!
#130000
b100 (
1!
#140000
0!
#150000
b101 (
1!
#160000
0!
#170000
b110 (
1!
#180000
0!
#190000
b111 (
1!
#200000
0!
#210000
b1000 (
1!
#220000
0!
#230000
b1001 (
1!
#240000
0!
#250000
b1010 (
1!
#260000
0!
#270000
b1011 (
1!
#280000
0!
#290000
b1100 (
1!
#300000
0!
#310000
b1101 (
1!
#320000
0!
#330000
b1110 (
1!
#340000
0!
#350000
b1101 *
b1111 (
1!
#360000
0!
#370000
b1111 &
b1100 *
b0 (
b1101 )
1!
#380000
0!
#390000
b111000 %
b111000 ,
b1011 '
b1011 +
b1011 *
b1100 )
1!
#400000
0!
#410000
b1010 *
b1011 )
1!
#420000
0!
#430000
b1011 &
b1010 )
1!
#440000
0!
#450000
b1 (
1!
#460000
0!
#470000
b10 (
1!
#480000
0!
#490000
b11 (
1!
#500000
0!
#510000
b100 (
1!
#520000
0!
#530000
b101 (
1!
#540000
0!
#550000
b110 (
1!
#560000
0!
#570000
b111 (
1!
#580000
0!
#590000
b1000 (
1!
#600000
0!
#610000
b1001 (
1!
#620000
0!
#630000
b1010 (
1!
#640000
0!
#650000
b1011 (
1!
#660000
0!
#670000
b1100 (
1!
#680000
0!
#690000
b1101 (
1!
#700000
0!
#710000
b1110 (
1!
#720000
0!
#730000
b1001 *
b1111 (
1!
#740000
0!
#750000
b1111 &
b1000 *
b0 (
b1001 )
1!
#760000
0!
#770000
b110 %
b110 ,
b11 '
b11 +
b111 *
b1000 )
1!
#780000
0!
#790000
b110 *
b111 )
1!
#800000
0!
#810000
b1101 &
b110 )
1!
#820000
0!
#830000
b1 (
1!
#840000
0!
#850000
b10 (
1!
#860000
0!
#870000
b11 (
1!
#880000
0!
#890000
b100 (
1!
#900000
0!
#910000
b101 (
1!
#920000
0!
#930000
b110 (
1!
#940000
0!
#950000
b111 (
1!
#960000
0!
#970000
b1000 (
1!
#980000
0!
#990000
b1001 (
1!
#1000000
0!
#1010000
b1010 (
1!
#1020000
0!
#1030000
b1011 (
1!
#1040000
0!
#1050000
b1100 (
1!
#1060000
0!
#1070000
b1101 (
1!
#1080000
0!
#1090000
b1110 (
1!
#1100000
0!
#1110000
b101 *
b1111 (
1!
#1120000
0!
#1130000
b1111 &
b100 *
b0 (
b101 )
1!
#1140000
0!
#1150000
b1001100 %
b1001100 ,
b100 '
b100 +
b11 *
b100 )
1!
#1160000
0!
#1170000
b10 *
b11 )
1!
#1180000
0!
#1190000
b1110 &
b10 )
1!
#1200000
0!
#1210000
b1 (
1!
#1220000
0!
#1230000
b10 (
1!
#1240000
0!
#1250000
b11 (
1!
#1260000
0!
#1270000
b100 (
1!
#1280000
0!
#1290000
b101 (
1!
#1300000
0!
#1310000
b110 (
1!
#1320000
0!
#1330000
b111 (
1!
#1340000
0!
#1350000
b1000 (
1!
#1360000
0!
#1370000
b1001 (
1!
#1380000
0!
#1390000
b1010 (
1!
#1400000
0!
#1410000
b1011 (
1!
#1420000
0!
#1430000
b1100 (
1!
#1440000
0!
#1450000
b1101 (
1!
#1460000
0!
#1470000
b1110 (
1!
#1480000
0!
#1490000
b1 *
b1111 (
1!
#1500000
0!
#1510000
b1111 &
b0 *
b0 (
b1 )
1!
#1520000
0!
#1530000
b1111110 %
b1111110 ,
b1010 '
b1010 +
b1111 *
b0 )
1!
#1540000
0!
#1550000
b1110 *
b1111 )
1!
#1560000
0!
#1570000
b111 &
b1110 )
1!
#1580000
0!
#1590000
b1 (
1!
