src/LedDecoder.v
module LedDecoder (
    output reg  [6:0] led,
    input  wire [3:0] char
);

  //        a
  //       ------
  //    f |      | b
  //      |  g   |
  //       ------
  //      |      |
  //    e |      | c
  //       ------
  //         d

  parameter CharHyphen = 10, CharF = 11, CharSpace = 12;

  always @(char) begin
    case (char)
      //                   abcdefg
      0:          led = 7'b0000001;
      1:          led = 7'b1001111;
      2:          led = 7'b0010010;
      3:          led = 7'b0000110;
      4:          led = 7'b1001100;
      5:          led = 7'b0100100;
      6:          led = 7'b1100000;
      7:          led = 7'b0001111;
      8:          led = 7'b0000000;
      9:          led = 7'b0001100;
      CharHyphen: led = 7'b1111110;
      CharF:      led = 7'b0111000;
      CharSpace:  led = 7'b1111111;
      default:    led = 7'b1111111;
    endcase
  end

endmodule

src/LedDecoder_tb.v
`timescale 1ns / 1ps
`include "LedDecoder.v"

module LedDecoder_tb;
  reg [3:0] char_tb;

  LedDecoder ledDec (.char(char_tb));

  initial begin
    $dumpfile("waveforms/LedDecoder.vcd");
    $dumpvars;
    char_tb = 0;
    for (integer i = 0; i < 13; i++) begin
      #10 char_tb = char_tb + 1;
    end
    #10 $finish;
  end

endmodule

waveforms/LedDecoder.vcd
$date
	Sat Dec 24 20:28:26 2022
$end
$version
	Icarus Verilog
$end
$timescale
	1ps
$end
$scope module LedDecoder_tb $end
$var reg 4 ! char_tb [3:0] $end
$scope module ledDec $end
$var wire 4 " char [3:0] $end
$var parameter 32 # CharF $end
$var parameter 32 $ CharHyphen $end
$var parameter 32 % CharSpace $end
$var reg 7 & led [6:0] $end
$upscope $end
$scope begin $ivl_for_loop0 $end
$var integer 32 ' i [31:0] $end
$upscope $end
$upscope $end
$enddefinitions $end
$comment Show the parameter values. $end
$dumpall
b1100 %
b1010 $
b1011 #
$end
#0
$dumpvars
b0 '
b1 &
b0 "
b0 !
$end
#10000
b1001111 &
b1 '
b1 !
b1 "
#20000
b10010 &
b10 '
b10 !
b10 "
#30000
b110 &
b11 '
b11 !
b11 "
#40000
b1001100 &
b100 '
b100 !
b100 "
#50000
b100100 &
b101 '
b101 !
b101 "
#60000
b1100000 &
b110 '
b110 !
b110 "
#70000
b1111 &
b111 '
b111 !
b111 "
#80000
b0 &
b1000 '
b1000 !
b1000 "
#90000
b1100 &
b1001 '
b1001 !
b1001 "
#100000
b1111110 &
b1010 '
b1010 !
b1010 "
#110000
b111000 &
b1011 '
b1011 !
b1011 "
#120000
b1111111 &
b1100 '
b1100 !
b1100 "
#130000
b1101 '
b1101 !
b1101 "
